README.md
setup.py
MonoBoost.egg-info/PKG-INFO
MonoBoost.egg-info/SOURCES.txt
MonoBoost.egg-info/dependency_links.txt
MonoBoost.egg-info/not-zip-safe
MonoBoost.egg-info/requires.txt
MonoBoost.egg-info/top_level.txt
monoboost/__init__.py
monoboost/monoboost.py
monoboost/version.py
monoboost/data/boston.csv
monoboost/tests/__init__.py
monoboost/tests/test_monoboost.py