Metadata-Version: 1.1
Name: MonoBoost
Version: 0.7
Summary: monoboost: a partially monotone instance based classification library
Home-page: http://github.com/chriswbartley/monoboost
Author: Christopher Bartley
Author-email: christopher.bartley@research.uwa.edu.au
License: MIT
Platform: OS Independent
Classifier: Development Status :: 3 - Alpha
Classifier: Environment :: Console
Classifier: Intended Audience :: Science/Research
Classifier: License :: OSI Approved :: MIT License
Classifier: Operating System :: OS Independent
Classifier: Programming Language :: Python
Classifier: Topic :: Scientific/Engineering
Requires: numpy
